vmail/__init__.py
vmail/alias.py
vmail/config.py
vmail/db.py
vmail/domain.py
vmail/helpers.py
vmail/user.py
vmail_cli-1.0.1.dist-info/LICENSE
vmail_cli-1.0.1.dist-info/METADATA
vmail_cli-1.0.1.dist-info/WHEEL
vmail_cli-1.0.1.dist-info/entry_points.txt
vmail_cli-1.0.1.dist-info/top_level.txt
vmail_cli-1.0.1.dist-info/RECORD
