Metadata-Version: 2.1
Name: vmail-cli
Version: 1.0.1
Summary: CLI to manage your vmail server (Dovecot, Postfix, MySQL)
Home-page: https://framagit.org/jlebleu/vmail-cli
Author: Jerome Lebleu
Author-email: jerome@maroufle.fr
License: MIT
Project-URL: Bug Tracker, https://framagit.org/jlebleu/vmail-cli/-/issues
Project-URL: Source Code, https://framagit.org/jlebleu/vmail-cli
Keywords: vmail,postfix,dovecot
Platform: UNKNOWN
Classifier: Development Status :: 3 - Alpha
Classifier: Intended Audience :: System Administrators
Classifier: License :: OSI Approved :: MIT License
Classifier: Operating System :: POSIX :: Linux
Classifier: Programming Language :: Python :: 3
Classifier: Programming Language :: Python :: 3.7
Classifier: Programming Language :: Python :: 3.8
Classifier: Programming Language :: Python :: 3.9
Classifier: Programming Language :: Python :: 3 :: Only
Classifier: Topic :: Communications :: Email
Requires-Python: >=3.7
Requires-Dist: click (>=7.0)
Requires-Dist: confuse (>=1.0)
Requires-Dist: passlib (>=1.7)
Requires-Dist: sqlalchemy (>=1.2)
Requires-Dist: tabulate (>=0.8)
Provides-Extra: test
Requires-Dist: black ; extra == 'test'
Requires-Dist: flake8-black ; extra == 'test'
Requires-Dist: flake8-isort ; extra == 'test'
Requires-Dist: flake8 (>=3.5) ; extra == 'test'
Requires-Dist: isort (>=5.0) ; extra == 'test'
